Metadata-Version: 2.1
Name: shiki.py
Version: 1.1.4
Summary: Python Async Wrapper for Shikimori Api
Home-page: https://github.com/Snayt1k3/shiki.py
Author: Snayt1k3
Author-email: snayt1k3@gmail.com
Classifier: License :: OSI Approved :: MIT License
Classifier: Programming Language :: Python :: 3
Classifier: Programming Language :: Python :: 3.10
Classifier: Programming Language :: Python :: 3.11
Classifier: Programming Language :: Python :: 3.12
License-File: LICENSE
Requires-Dist: aiohttp >=3.9.1
Requires-Dist: tomli >=2.0.1
Requires-Dist: setuptools >=69.0.3
Provides-Extra: readthedocs
Requires-Dist: furo ; extra == 'readthedocs'
Requires-Dist: readthedocs-sphinx-search ; extra == 'readthedocs'
Requires-Dist: Sphinx ; extra == 'readthedocs'
Requires-Dist: sphinx-hoverxref ; extra == 'readthedocs'
